libsan/__about__.py
libsan/__init__.py
libsan/sancli.py
libsan/sanmgmt.py
libsan/array/dell/__init__.py
libsan/array/dell/eqlogic.py
libsan/array/dell/eqlparse_show.py
libsan/array/emc/__init__.py
libsan/array/emc/vnx.py
libsan/array/linux/__init__.py
libsan/array/linux/lio.py
libsan/array/netapp/__init__.py
libsan/array/netapp/ontap.py
libsan/array/netapp/ontap8.py
libsan/host/__init__.py
libsan/host/cli_tools.py
libsan/host/cmdline.py
libsan/host/conf.py
libsan/host/dm.py
libsan/host/dmpd.py
libsan/host/dt.py
libsan/host/fc.py
libsan/host/fcoe.py
libsan/host/fio.py
libsan/host/iscsi.py
libsan/host/linux.py
libsan/host/lio.py
libsan/host/loopdev.py
libsan/host/lsm.py
libsan/host/lvm.py
libsan/host/md.py
libsan/host/mp.py
libsan/host/net.py
libsan/host/nvme.py
libsan/host/qemu_img.py
libsan/host/scsi.py
libsan/host/scsi_debug.py
libsan/host/snapper.py
libsan/host/ssh.py
libsan/host/stratis.py
libsan/host/targetd.py
libsan/host/vdo.py
libsan/misc/__init__.py
libsan/misc/array.py
libsan/misc/size.py
libsan/misc/time.py
libsan/physwitch/apcon/__init__.py
libsan/physwitch/apcon/apconcli.py
libsan/switch/brocade/__init__.py
libsan/switch/brocade/fos.py
libsan/switch/cisco/__init__.py
libsan/switch/cisco/nxos.py
libsan-0.5.10.dist-info/METADATA
libsan-0.5.10.dist-info/WHEEL
libsan-0.5.10.dist-info/entry_points.txt
libsan-0.5.10.dist-info/licenses/LICENSE
libsan-0.5.10.dist-info/RECORD
