Metadata-Version: 2.4
Name: libsan
Version: 0.5.10
Summary: Python modules to manage SAN devices
Project-URL: Repository, https://gitlab.com/rh-kernel-stqe/python-libsan
Author-email: Bruno Goncalves <bgoncalv@redhat.com>
Maintainer-email: Bruno Goncalves <bgoncalv@redhat.com>, Martin Hoyer <mhoyer@redhat.com>, Filip Suba <fsuba@redhat.com>
License-Expression: GPL-3.0-or-later
License-File: LICENSE
Classifier: License :: OSI Approved :: GNU General Public License v3 or later (GPLv3+)
Classifier: Programming Language :: Python :: 3
Classifier: Programming Language :: Python :: 3 :: Only
Classifier: Programming Language :: Python :: 3.6
Classifier: Programming Language :: Python :: 3.7
Classifier: Programming Language :: Python :: 3.8
Classifier: Programming Language :: Python :: 3.9
Classifier: Programming Language :: Python :: 3.10
Classifier: Programming Language :: Python :: 3.11
Requires-Python: >=3.6
Requires-Dist: configobj>=5.0.8
Requires-Dist: netapp-ontap>=9.11.1.0
Requires-Dist: netifaces2<=0.0.19,>=0.0.13; python_version <= '3.6'
Requires-Dist: netifaces2>=0.0.13; python_version > '3.6'
Requires-Dist: requests>=2.27.1
Provides-Extra: ssh
Requires-Dist: ssh2-python<1.2.0,>=1.0.0; (python_version <= '3.6') and extra == 'ssh'
Requires-Dist: ssh2-python>=1.0.0; (python_version > '3.6') and extra == 'ssh'
